barectf/__init__.py
barectf/argpar.py
barectf/cgen.py
barectf/cli.py
barectf/codegen.py
barectf/config.py
barectf/config_file.py
barectf/config_parse.py
barectf/config_parse_common.py
barectf/config_parse_v2.py
barectf/config_parse_v3.py
barectf/include/2/lttng-ust-log-levels.yaml
barectf/include/2/stdfloat.yaml
barectf/include/2/stdint.yaml
barectf/include/2/stdmisc.yaml
barectf/include/2/trace-basic.yaml
barectf/include/3/lttng-ust-log-levels.yaml
barectf/include/3/stdint.yaml
barectf/include/3/stdmisc.yaml
barectf/include/3/stdreal.yaml
barectf/schemas/config/2/clock-type-pre-include.yaml
barectf/schemas/config/2/config-min.yaml
barectf/schemas/config/2/config-pre-field-type-expansion.yaml
barectf/schemas/config/2/config-pre-include.yaml
barectf/schemas/config/2/config.yaml
barectf/schemas/config/2/dst-pre-include.yaml
barectf/schemas/config/2/ert-pre-include.yaml
barectf/schemas/config/2/field-type.yaml
barectf/schemas/config/2/include-prop.yaml
barectf/schemas/config/2/metadata-pre-include.yaml
barectf/schemas/config/2/trace-type-pre-include.yaml
barectf/schemas/config/3/clock-type-pre-include.yaml
barectf/schemas/config/3/config-pre-field-type-expansion.yaml
barectf/schemas/config/3/config-pre-include.yaml
barectf/schemas/config/3/config-pre-log-level-alias-sub.yaml
barectf/schemas/config/3/config.yaml
barectf/schemas/config/3/dst-pre-include.yaml
barectf/schemas/config/3/ert-pre-include.yaml
barectf/schemas/config/3/field-type.yaml
barectf/schemas/config/3/include-prop.yaml
barectf/schemas/config/3/trace-pre-include.yaml
barectf/schemas/config/3/trace-type-pre-include.yaml
barectf/schemas/config/common/common.yaml
barectf/template.py
barectf/templates/c/align-statements-comment.j2
barectf/templates/c/barectf.c-macros.j2
barectf/templates/c/barectf.c.j2
barectf/templates/c/barectf.h.j2
barectf/templates/c/bitfield.h.j2
barectf/templates/c/close-func-proto.j2
barectf/templates/c/common.j2
barectf/templates/c/ctx-init-func-proto.j2
barectf-3.1.2.dist-info/LICENSE
barectf-3.1.2.dist-info/METADATA
barectf-3.1.2.dist-info/WHEEL
barectf-3.1.2.dist-info/entry_points.txt
barectf-3.1.2.dist-info/RECORD
